beehve-3.0.0.dev5.dist-info/METADATA
beehve-3.0.0.dev5.dist-info/entry_points.txt
beehve-3.0.0.dev5.dist-info/metadata.json
beehve-3.0.0.dev5.dist-info/DESCRIPTION.rst
beehve-3.0.0.dev5.dist-info/RECORD
beehve-3.0.0.dev5.dist-info/top_level.txt
beehve-3.0.0.dev5.dist-info/WHEEL
beehve/__init__.py
beehve/settings.py
beehve/celery.py
beehve/urls.py
beehve/wsgi.py
beehve/manage_beehve.py
beehve/apps/__init__.py
beehve/apps/workers/__init__.py
beehve/apps/workers/models.py
beehve/apps/workers/urls.py
beehve/apps/workers/tags.py
beehve/apps/workers/forms.py
beehve/apps/workers/tests.py
beehve/apps/workers/views.py
beehve/apps/workers/admin.py
beehve/apps/workers/backends.py
beehve/apps/workers/migrations/__init__.py
beehve/apps/workers/migrations/0002_auto_20141230_2349.py
beehve/apps/workers/migrations/0001_initial.py
beehve/apps/workers/migrations/__pycache__/0002_auto_20141230_2349.cpython-35.pyc
beehve/apps/workers/migrations/__pycache__/__init__.cpython-35.pyc
beehve/apps/workers/migrations/__pycache__/0001_initial.cpython-35.pyc
beehve/apps/workers/__pycache__/__init__.cpython-35.pyc
beehve/apps/workers/__pycache__/backends.cpython-35.pyc
beehve/apps/workers/__pycache__/urls.cpython-35.pyc
beehve/apps/workers/__pycache__/models.cpython-35.pyc
beehve/apps/workers/__pycache__/admin.cpython-35.pyc
beehve/apps/workers/__pycache__/views.cpython-35.pyc
beehve/apps/workers/__pycache__/forms.cpython-35.pyc
beehve/apps/workers/templatetags/__init__.py
beehve/apps/workers/templatetags/__pycache__/volunteer_tags.cpython-35.pyc
beehve/apps/workers/templatetags/__pycache__/__init__.cpython-35.pyc
beehve/apps/honey/__init__.py
beehve/apps/honey/models.py
beehve/apps/honey/utils.py
beehve/apps/honey/urls.py
beehve/apps/honey/forms.py
beehve/apps/honey/tasks.py
beehve/apps/honey/tests.py
beehve/apps/honey/views.py
beehve/apps/honey/admin.py
beehve/apps/honey/idea_urls.py
beehve/apps/honey/context_processors.py
beehve/apps/honey/project_urls.py
beehve/apps/honey/migrations/__init__.py
beehve/apps/honey/migrations/0001_initial.py
beehve/apps/honey/migrations/0001_initial.py.bak
beehve/apps/honey/migrations/__pycache__/__init__.cpython-35.pyc
