Metadata-Version: 2.0
Name: beehve
Version: 3.0.0.dev5
Summary: An beehve for django applications.
Home-page: http://github.com/powellc/beehve
Author: Colin Powell
Author-email: colin.powell@gmail.com
License: BSD
Platform: OS Independent
Classifier: Development Status :: 4 - Beta
Classifier: Framework :: Django
Classifier: Intended Audience :: Developers
Classifier: License :: OSI Approved :: BSD License
Classifier: Operating System :: OS Independent
Classifier: Programming Language :: Python
Classifier: Topic :: Internet :: WWW/HTTP
Classifier: Topic :: Internet :: WWW/HTTP :: Dynamic Content
Requires-Dist: Django (>=1.10)
Requires-Dist: django-configurations (>=2.0)
Requires-Dist: dj-database-url (>=0.3.0)
Requires-Dist: Pillow (>=3.0.0)
Requires-Dist: django-cache-url (>=0.8.0)
Requires-Dist: werkzeug (>=0.9.4)
Requires-Dist: gunicorn (>=0.19.0)
Requires-Dist: easy-thumbnails (>=1.2)
Requires-Dist: django-debug-toolbar (>=1.1)
Requires-Dist: django-extensions (>=1.3.4)
Requires-Dist: django-braces (>=1.4.0)
Requires-Dist: django-allauth (>=0.16.1)
Requires-Dist: django-floppyforms (>=1.1.1)
Requires-Dist: django-custom-user (>=0.4)
Requires-Dist: django-markdown-deux (>=1.0.4)
Requires-Dist: django-avatar (>=2.0)
Requires-Dist: django-localflavor (>=1.0.0)
Requires-Dist: gittle3 (>=0.6.0)
Requires-Dist: celery[redis] (>=3.1.16,<4)
Requires-Dist: django-celery (>=3.1.16)
Requires-Dist: django-bower (>=5.0.1)
Requires-Dist: django-bootstrap3 (>=4.8.1)
Requires-Dist: raven (>=5.0.0)
Requires-Dist: pytz (>=2014.7)
Requires-Dist: shortuuid (>=0.4.2)
Provides-Extra: postgres
Requires-Dist: psycopg2; extra == 'postgres'
